[{"word":"boîte (f) (en carton)","meaning":"box (cardboard)","category":"Kitchen"},{"word":"bouteille (f)","meaning":"bottle","category":"Kitchen"},{"word":"chaise (f)","meaning":"chair","category":"Kitchen"},{"word":"cuisine (f)","meaning":"kitchen","category":"Kitchen"},{"word":"évier (m)","meaning":"sink","category":"Kitchen"},{"word":"casserole (f)","meaning":"saucepan","category":"Kitchen"},{"word":"poêle (f)","meaning":"frying pan","category":"Kitchen"},{"word":"couvercle (m)","meaning":"lid","category":"Kitchen"},{"word":"four (m)","meaning":"oven","category":"Kitchen"},{"word":"four à micro-ondes (m)","meaning":"microwave oven","category":"Kitchen"},{"word":"réfrigérateur (m)","meaning":"fridge","category":"Kitchen"},{"word":"congélateur (m)","meaning":"freezer","category":"Kitchen"},{"word":"placard (m)","meaning":"cupboard","category":"Kitchen"},{"word":"tiroir (m)","meaning":"drawer","category":"Kitchen"},{"word":"planche à découper (f)","meaning":"cutting board","category":"Kitchen"},{"word":"couteau (m)","meaning":"knife","category":"Kitchen"},{"word":"fourchette (f)","meaning":"fork","category":"Kitchen"},{"word":"cuillère (f)","meaning":"spoon","category":"Kitchen"},{"word":"louche (f)","meaning":"ladle","category":"Kitchen"},{"word":"verre (m)","meaning":"glass","category":"Kitchen"},{"word":"tasse (f)","meaning":"cup","category":"Kitchen"},{"word":"bol (m)","meaning":"bowl","category":"Kitchen"},{"word":"assiette (f)","meaning":"plate","category":"Kitchen"},{"word":"passoire (f)","meaning":"colander / strainer","category":"Kitchen"},{"word":"ouvre-boîte (m)","meaning":"can opener","category":"Kitchen"},{"word":"mixeur (m)","meaning":"blender / mixer","category":"Kitchen"},{"word":"grille-pain (m)","meaning":"toaster","category":"Kitchen"},{"word":"bouilloire (f)","meaning":"kettle","category":"Kitchen"},{"word":"torchon (m)","meaning":"tea towel","category":"Kitchen"},{"word":"éponge (f)","meaning":"sponge","category":"Kitchen"},{"word":"savon (m) de vaisselle","meaning":"dish soap","category":"Kitchen"}]